pytest_doctest_ufunc.py
pytest_doctest_ufunc-0.1.4.dist-info/LICENSE
pytest_doctest_ufunc-0.1.4.dist-info/METADATA
pytest_doctest_ufunc-0.1.4.dist-info/WHEEL
pytest_doctest_ufunc-0.1.4.dist-info/entry_points.txt
pytest_doctest_ufunc-0.1.4.dist-info/top_level.txt
pytest_doctest_ufunc-0.1.4.dist-info/RECORD
