Metadata-Version: 2.1
Name: pytest-doctest-ufunc
Version: 0.1.4
Summary: A plugin to run doctests in docstrings of Numpy ufuncs
Home-page: https://github.com/lpsinger/pytest-doctest-ufunc
Author: Leo Singer
Author-email: leo.singer@ligo.org
Maintainer: Leo Singer
Maintainer-email: leo.singer@ligo.org
License: MIT
Platform: UNKNOWN
Classifier: Development Status :: 7 - Inactive
Classifier: Framework :: Pytest
Classifier: Intended Audience :: Developers
Classifier: Topic :: Software Development :: Testing
Classifier: Programming Language :: Python
Classifier: Programming Language :: Python :: 3
Classifier: Programming Language :: Python :: 3.6
Classifier: Programming Language :: Python :: 3.7
Classifier: Programming Language :: Python :: 3.8
Classifier: Programming Language :: Python :: Implementation :: CPython
Classifier: Operating System :: OS Independent
Classifier: License :: OSI Approved :: MIT License
Requires-Python: >=3.6
License-File: LICENSE
Requires-Dist: numpy
Requires-Dist: pytest (>=3.5.0)
